<?xml version='1.0' encoding='utf-8'?><m:page id='6b4f6465-4b30-45ad-b0fa-6b09bbfa6096' xmlns='http://www.w3.org/1999/xhtml' title='Review New edit' xmlns:m='http://schemas.mendix.com/forms/1.0'><m:layouts><m:layout path='Atlas_Core/PopupLayout.layout.xml'></m:layout></m:layouts><m:arguments><m:argument parameterName='b4596b06-cd01-4e76-849a-093956f88892'><div class='mx-layoutgrid mx-layoutgrid-fluid container-fluid mx-name-layoutGrid1'><div class='row'><div class='col-lg-12 col-md-12 col-12'><div data-mendix-id='50.UGS.Review_NewEdit.dataView1' data-mendix-type='mxui.widget.DataView' data-mendix-props='"entity":"UGS.ReviewQ","datasource":{"type":"direct","path":"UGS.ReviewQ","queryId":"k+iYOSOhFk+Z2dPc669hTg"},"conditions":{}' class='mx-name-dataView1 form-horizontal' tabindex='0'></div></div></div></div></m:argument></m:arguments><m:templates><m:template widget-id='50.UGS.Review_NewEdit.dataView1' name='content'><div data-mendix-id='50.UGS.Review_NewEdit.referenceSelector1' class='form-group mx-referenceselector mx-name-referenceSelector1'><div data-mendix-id='50.4' data-mendix-type='mxui.widget.ReactWidgetWrapper' data-mendix-props='"widgetTree":[{"$widgetId":"50.4","widget":"Label","props":{"caption":{"$type":"ExpressionProperty","expression":{"expr":{"type":"literal","value":"Review Questions"},"args":{}}},"id":{"$type":"DerivedUniqueIdProperty","widgetId":"50.4"},"class":"control-label col-sm-3"}}],"listenTargets":[]'></div><div class='col-sm-9'><div data-mendix-id='50.UGS.Review_NewEdit.referenceSelector1$control' data-mendix-type='mxui.widget.ReferenceSelector' data-mendix-props='"showLabel":true,"attributePath":"UGS.ReviewQ/UGS.Review_Questions_ReviewQ/UGS.Review_Questions/Question","readOnlyStyle":"control","attributePath":"UGS.ReviewQ/UGS.Review_Questions_ReviewQ/UGS.Review_Questions/Question","datasource":{"type":"database","path":"UGS.Review_Questions","offlineConstraints":null,"constraint":"","sort":[["Question","asc"]]},"events":{"change":{"type":"callMicroflow","argMap":{"ReviewForm":{"widget":"$pageParameter","source":"object"}},"config":{"name":"UGS.OCH_OtherQuestion","validate":"view","allowedRoles":["GrantApplicationManager","Pannel_Interviewers"]},"disabledDuringExecution":false}},"validation":null,"renderMode":"Drop-down","emptyOptionCaption":""' tabindex='0'></div></div></div></m:template><m:template widget-id='50.UGS.Review_NewEdit.dataView1' name='footer'><div data-mendix-id='50.UGS.Review_NewEdit.actionButton2' data-mendix-type='mxui.widget.ReactWidgetWrapper' data-mendix-props='"widgetTree":[{"$widgetId":"50.UGS.Review_NewEdit.actionButton2","widget":"ActionButton","props":{"buttonId":"50.UGS.Review_NewEdit.actionButton2","class":"mx-name-actionButton2 cancel","renderType":"button","buttonClass":"btn-default","caption":{"$type":"ExpressionProperty","expression":{"expr":{"type":"literal","value":"Cancel"},"args":{}}},"tooltip":{"$type":"TextProperty","value":""},"action":{"$type":"ActionProperty","action":{"type":"cancelChanges","argMap":{},"config":{"closePage":true},"disabledDuringExecution":true},"abortOnServerValidation":true}}}],"listenTargets":[]'></div></m:template></m:templates></m:page>