<?xml version='1.0' encoding='utf-8'?><m:page id='68a0b80c-8386-49a2-bd03-4f27f5812be0' xmlns='http://www.w3.org/1999/xhtml' title='Password Recovery Sent' xmlns:m='http://schemas.mendix.com/forms/1.0'><m:layouts><m:layout path='ForgotPassword/ModalPopupLayout.layout.xml'></m:layout></m:layouts><m:arguments><m:argument parameterName='5083d00a-5376-42f3-b5af-7b90281e30c7'><div data-mendix-id='263.ForgotPassword.Step2_ConfirmationMessageSignup.label' data-mendix-type='mxui.widget.ReactWidgetWrapper' data-mendix-props='"widgetTree":[{"$widgetId":"263.ForgotPassword.Step2_ConfirmationMessageSignup.label","widget":"Label","props":{"class":"mx-name-label","id":{"$type":"DerivedUniqueIdProperty","widgetId":"263.ForgotPassword.Step2_ConfirmationMessageSignup.label"},"caption":{"$type":"TextProperty","value":"We have sent you a confirmation email.\r\nFollow the instructions in the confirmation email to setup your account"}}}],"listenTargets":[]'></div></m:argument></m:arguments></m:page>